ranker/__init__.py
ranker/__main__.py
ranker/modules/__init__.py
ranker/modules/main.py
ranker/modules/ranker.py
tests/__init__.py
tests/test_ranking.py
ranker-0.0.1.dist-info/LICENSE
ranker-0.0.1.dist-info/METADATA
ranker-0.0.1.dist-info/WHEEL
ranker-0.0.1.dist-info/entry_points.txt
ranker-0.0.1.dist-info/top_level.txt
ranker-0.0.1.dist-info/RECORD
