Metadata-Version: 2.1
Name: ranker
Version: 0.0.1
Summary: Generates rankings
Home-page: https://github.com/julianlefunk/ranker
Author: Julian Colmenares
Author-email: juliancpelayo@protonmail.com
Classifier: Programming Language :: Python :: 3
Classifier: License :: OSI Approved :: MIT License
Classifier: Operating System :: OS Independent
Requires-Python: >=3.7
License-File: LICENSE
